<?xml version="1.0" encoding="utf-8"?>
<form ID="corAPP-7052" sfwActive="True" sfwStatus="Valid" sfwRemoteObject="busDeathNotification" sfwType="Correspondence" sfwTemplate="APP-7052.docx" version="4.0" sfwEntity="entDeathNotification">
  <sfwFieldBookMarks>
    <sfwFieldBookMark ID="deceasedFirstName" sfwDataType="String" sfwEntityField="objPerson.IstrFirstNameInTitleCase" />
    <sfwFieldBookMark ID="deceasedName" sfwDataType="String" sfwEntityField="objPerson.FullNameCaps" />
    <sfwFieldBookMark ID="deceasedPERSLinkID" sfwDataType="Int" sfwEntityField="objPerson.PersonId" />
    <sfwFieldBookMark ID="LifeInsurancePolicyValue" sfwDataFormat="{0:C}" sfwDataType="Decimal" sfwEntityField="IdecLifeInsurancePolicyValue" />
    <sfwFieldBookMark ID="PlanId" sfwDataType="Int" />
    <sfwFieldBookMark ID="ImgImage" sfwDataType="sfwImageFile" sfwImageWidth="8.5" sfwEntityField="IstrImage" />
  </sfwFieldBookMarks>
  <sfwQueryBookMarks>
    <sfwQueryBookMark ID="Name" sfwDataType="String" />
    <sfwQueryBookMark ID="AdrCorStreet1" />
    <sfwQueryBookMark ID="AdrCorStreet2" />
    <sfwQueryBookMark ID="AdrCorCity" />
    <sfwQueryBookMark ID="AdrCorState" />
    <sfwQueryBookMark ID="AdrCorZip" />
    <sfwQueryBookMark ID="Salutation" />
    <sfwQueryBookMark ID="DeceasedBeneficiaryFirstName" />
    <sfwQueryBookMark ID="PrimaryBeneficiaryIsDeceased" />
  </sfwQueryBookMarks>
  <sfwQueryForm>
    <sfwTable ID="tblCriteria">
      <sfwRow>
        <sfwColumn>
          <sfwLabel ID="capPrimaryBeneficiaryFirstName" Text="Beneficiary First Name :" sfwIsCaption="True" />
        </sfwColumn>
        <sfwColumn>
          <sfwTextBox ID="PrimaryBeneficiaryFirstName" sfwQueryID="DeceasedBeneficiaryFirstName" />
        </sfwColumn>
      </sfwRow>
      <sfwRow>
        <sfwColumn>
          <sfwLabel ID="capBeneAdrCorStreet1" Text="Address Line 1 :" sfwIsCaption="True" />
        </sfwColumn>
        <sfwColumn>
          <sfwTextBox ID="BeneAdrCorStreet1" sfwQueryID="AdrCorStreet1" />
        </sfwColumn>
      </sfwRow>
      <sfwRow>
        <sfwColumn>
          <sfwLabel ID="capBeneAdrCorStreet2" Text="Address Line 2 :" sfwIsCaption="True" />
        </sfwColumn>
        <sfwColumn>
          <sfwTextBox ID="BeneAdrCorStreet2" sfwQueryID="AdrCorStreet2" />
        </sfwColumn>
      </sfwRow>
      <sfwRow>
        <sfwColumn>
          <sfwLabel ID="capBeneAdrCorCity" Text="Address City :" sfwIsCaption="True" />
        </sfwColumn>
        <sfwColumn>
          <sfwTextBox ID="BeneAdrCorCity" sfwQueryID="AdrCorCity" />
        </sfwColumn>
      </sfwRow>
      <sfwRow>
        <sfwColumn>
          <sfwLabel ID="capBeneAdrCorState" Text="Address State :" sfwIsCaption="True" />
        </sfwColumn>
        <sfwColumn>
          <sfwTextBox ID="BeneAdrCorState" sfwQueryID="AdrCorState" />
        </sfwColumn>
      </sfwRow>
      <sfwRow>
        <sfwColumn>
          <sfwLabel ID="capBeneAdrCorZip" Text="Address Zip :" sfwIsCaption="True" />
        </sfwColumn>
        <sfwColumn>
          <sfwTextBox ID="BeneAdrCorZip" sfwQueryID="AdrCorZip" />
        </sfwColumn>
      </sfwRow>
      <sfwRow>
        <sfwColumn>
          <sfwLabel ID="capPrimaryBeneficiaryIsDeceased1" Text="Is Primary Beneficiary Deceased :" sfwIsCaption="True" />
        </sfwColumn>
        <sfwColumn>
          <sfwRadioButtonList ID="sfwRadioButtonList" sfwQueryID="PrimaryBeneficiaryIsDeceased" sfwLoadType="Items">
            <ListItem Text="Yes" Value="Y" />
          </sfwRadioButtonList>
        </sfwColumn>
      </sfwRow>
      <sfwRow>
        <sfwColumn>
          <sfwLabel ID="capSalutation" Text="Beneficiary Salutation :" sfwIsCaption="True" />
        </sfwColumn>
        <sfwColumn>
          <sfwTextBox ID="Salutation" sfwQueryID="Salutation" />
        </sfwColumn>
      </sfwRow>
      <sfwRow>
        <sfwColumn>
          <sfwLabel ID="capName" Text="Beneficiary Name :" sfwIsCaption="True" />
        </sfwColumn>
        <sfwColumn>
          <sfwTextBox ID="Name" sfwQueryID="Name" />
        </sfwColumn>
      </sfwRow>
    </sfwTable>
  </sfwQueryForm>
</form>