[
  {
    "PROCESS_ID": 211,
    "DESCRIPTION": "Contact Ticket Transfer Call",
    "name": "nfmContactTicketTransferCall",
    "Activities": [
      {
        "ACTIVITY_ID": 184,
        "NAME": "Fulfill Customer Information Request",
        "DISPLAY_NAME": "Fulfill Customer Information Request"
      }
    ]
  },
  {
    "PROCESS_ID": 212,
    "DESCRIPTION": "Contact Ticket Schedule Appointment",
    "name": "nfmContactTicketScheduleAppointment",
    "Activities": [
      {
        "ACTIVITY_ID": 185,
        "NAME": "Conduct Appointment",
        "DISPLAY_NAME": "Conduct_Appointment"
      }
    ]
  },
  {
    "PROCESS_ID": 213,
    "DESCRIPTION": "Contact Ticket Schedule Seminar",
    "name": "nfmContactTicketScheduleSeminar",
    "Activities": [
      {
        "ACTIVITY_ID": 186,
        "NAME": "Setup Seminar",
        "DISPLAY_NAME": "Setup_Seminar"
      }
    ]
  },
  {
    "PROCESS_ID": 214,
    "DESCRIPTION": "Enroll Membership",
    "name": "nfmEnrollMembership",
    "Activities": [
      {
        "ACTIVITY_ID": 1,
        "NAME": "Create And Maintain Person Information",
        "DISPLAY_NAME": "Create And Maintain Person Information"
      },
      {
        "ACTIVITY_ID": 2,
        "NAME": "Audit Member Information",
        "DISPLAY_NAME": "Audit Member Information"
      }
    ]
  },
  {
    "PROCESS_ID": 215,
    "DESCRIPTION": "Add POA/Guardian",
    "name": "nfmAddPOAorGuardian",
    "Activities": [
      {
        "ACTIVITY_ID": 351,
        "NAME": "Review Legal Documents",
        "DISPLAY_NAME": "Review Legal Documents"
      },
      {
        "ACTIVITY_ID": 187,
        "NAME": "Enter Contact Information",
        "DISPLAY_NAME": "Enter_Contact_Information"
      },
      {
        "ACTIVITY_ID": 188,
        "NAME": "Review Contact Information",
        "DISPLAY_NAME": "Review_Contact_Information"
      }
    ]
  },
  {
    "PROCESS_ID": 220,
    "DESCRIPTION": "Fulfill Service Credit Purchase Query",
    "name": "nfmFulfillServiceCreditPurchaseQuery",
    "Activities": [
      {
        "ACTIVITY_ID": 8,
        "NAME": "Prepare Cost Statement",
        "DISPLAY_NAME": "Prepare Cost Statement"
      },
      {
        "ACTIVITY_ID": 9,
        "NAME": "Audit Prepare Cost Statement",
        "DISPLAY_NAME": "Audit Prepare Cost Statement"
      },
      {
        "ACTIVITY_ID": 10,
        "NAME": "Generate Service Credit Purchase Letter",
        "DISPLAY_NAME": "Generate Service Credit Purchase Letter"
      }
    ]
  },
  {
    "PROCESS_ID": 221,
    "DESCRIPTION": "Process Service Credit Purchase Election and Payment",
    "name": "nfmProcessServiceCreditPurchaseElectionandPayment",
    "Activities": [
      {
        "ACTIVITY_ID": 3,
        "NAME": "Verify Purchase Documents",
        "DISPLAY_NAME": "Verify Purchase Documents"
      },
      {
        "ACTIVITY_ID": 4,
        "NAME": "Setup Purchase Contract",
        "DISPLAY_NAME": "Setup Purchase Contract"
      },
      {
        "ACTIVITY_ID": 5,
        "NAME": "Audit Setup Purchase Contract",
        "DISPLAY_NAME": "Audit Setup Purchase Contract"
      },
      {
        "ACTIVITY_ID": 6,
        "NAME": "Apply Service Credit Remittance",
        "DISPLAY_NAME": "Apply Service Credit Remittance"
      },
      {
        "ACTIVITY_ID": 7,
        "NAME": "Allocate Service Credit Purchase Remittance",
        "DISPLAY_NAME": "Allocate Service Credit Purchase Remittance"
      }
    ]
  },
  {
    "PROCESS_ID": 224,
    "DESCRIPTION": "Resolve Additional Purchase Payment",
    "name": "nfmResolveAdditionalPurchasePayment",
    "Activities": [
      {
        "ACTIVITY_ID": 11,
        "NAME": "Apply Service Credit Remittance",
        "DISPLAY_NAME": "Apply Service Credit Remittance"
      },
      {
        "ACTIVITY_ID": 12,
        "NAME": "Allocate Service Credit Purchase Remittance",
        "DISPLAY_NAME": "Allocate Service Credit Purchase Remittance"
      }
    ]
  },
  {
    "PROCESS_ID": 229,
    "DESCRIPTION": "Enroll New Hire in Pension and Insurance Plans",
    "name": "nfmEnrollNewHireinPensionandInsurancePlans",
    "Activities": [
      {
        "ACTIVITY_ID": 13,
        "NAME": "Enter Plan Enrollment Data",
        "DISPLAY_NAME": "Enter Plan Enrollment Data"
      },
      {
        "ACTIVITY_ID": 14,
        "NAME": "Audit Plan Enrollment Data",
        "DISPLAY_NAME": "Audit Plan Enrollment Data"
      }
    ]
  },
  {
    "PROCESS_ID": 230,
    "DESCRIPTION": "Manage Medicare Age 65 Letter",
    "name": "nfmManageMedicareAge65Letter",
    "Activities": [
      {
        "ACTIVITY_ID": 15,
        "NAME": "Generate Medicare Age65 Followup Letter",
        "DISPLAY_NAME": "Generate Medicare Age 65 Follow-up Letter"
      }
    ]
  },
  {
    "PROCESS_ID": 231,
    "DESCRIPTION": "Transition Insurance Coverages",
    "name": "nfmTransitionInsuranceCoverages",
    "Activities": [
      {
        "ACTIVITY_ID": 16,
        "NAME": "Process Payee Insurance",
        "DISPLAY_NAME": "Process Payee Insurance"
      },
      {
        "ACTIVITY_ID": 17,
        "NAME": "Audit Process Payee Insurance",
        "DISPLAY_NAME": "Audit Process Payee Insurance"
      }
    ]
  },
  {
    "PROCESS_ID": 232,
    "DESCRIPTION": "Maintain Payee Benefit Plan",
    "name": "nfmMaintainPayeeBenefitPlan",
    "Activities": [
      {
        "ACTIVITY_ID": 18,
        "NAME": "Update Payee Benefit Plan",
        "DISPLAY_NAME": "Update Payee Benefit Plan"
      },
      {
        "ACTIVITY_ID": 19,
        "NAME": "Audit Update Payee Benefit Plan",
        "DISPLAY_NAME": "Audit Update Payee Benefit Plan"
      },
      {
        "ACTIVITY_ID": 20,
        "NAME": "Send Acknowledgement Letter",
        "DISPLAY_NAME": "Send Acknowledgment Letter"
      }
    ]
  },
  {
    "PROCESS_ID": 233,
    "DESCRIPTION": "Notice of Transfer SFN 53506",
    "name": "nfmNoticeofTransferSFN53506",
    "Activities": [
      {
        "ACTIVITY_ID": 21,
        "NAME": "Transfer Employment",
        "DISPLAY_NAME": "Transfer Employment"
      },
      {
        "ACTIVITY_ID": 22,
        "NAME": "Audit Transfer Employment",
        "DISPLAY_NAME": "Audit Transfer Employment"
      }
    ]
  },
  {
    "PROCESS_ID": 234,
    "DESCRIPTION": "Transfer to TFFR or TIAA CREF",
    "name": "nfmTransfertoTFFRorTIAACREF",
    "Activities": [
      {
        "ACTIVITY_ID": 23,
        "NAME": "Prepare TFFR or TIAA CREF Transfer",
        "DISPLAY_NAME": "Prepare TFFR or TIAA-CREF Transfer"
      },
      {
        "ACTIVITY_ID": 24,
        "NAME": "Audit Prepare TFFR or TIAA CREF Transfer",
        "DISPLAY_NAME": "Audit Prepare TFFR or TIAA-CREF Transfer "
      }
    ]
  },
  {
    "PROCESS_ID": 235,
    "DESCRIPTION": "Transfer to DC",
    "name": "nfmTransfertoDC",
    "Activities": [
      {
        "ACTIVITY_ID": 25,
        "NAME": "Prepare DC Transfer",
        "DISPLAY_NAME": "Prepare DC Transfer"
      },
      {
        "ACTIVITY_ID": 26,
        "NAME": "Audit Prepare DC Transfer",
        "DISPLAY_NAME": "Audit Prepare DC Transfer"
      }
    ]
  },
  {
    "PROCESS_ID": 236,
    "DESCRIPTION": "Process DB Retirement Application",
    "name": "nfmProcessDBRetirementApplication",
    "Activities": [
      {
        "ACTIVITY_ID": 27,
        "NAME": "Enter Retirement Application Data",
        "DISPLAY_NAME": "Enter Retirement Application Data"
      },
      {
        "ACTIVITY_ID": 33,
        "NAME": "Approve Retirement Application Calculation",
        "DISPLAY_NAME": "Approve Retirement Application Calculation"
      },
      {
        "ACTIVITY_ID": 34,
        "NAME": "Enter Payee Account Details",
        "DISPLAY_NAME": "Enter Payee Account Details"
      },
      {
        "ACTIVITY_ID": 35,
        "NAME": "Approve Payee Account",
        "DISPLAY_NAME": "Approve Payee Account"
      }
    ]
  },
  {
    "PROCESS_ID": 237,
    "DESCRIPTION": "Process Job Service Retirement Application",
    "name": "nfmProcessJobServiceRetirementApplication",
    "Activities": [
      {
        "ACTIVITY_ID": 32,
        "NAME": "Enter Job Service Retirement Application Data",
        "DISPLAY_NAME": "Enter Job Service Retirement Application Data"
      },
      {
        "ACTIVITY_ID": 49,
        "NAME": "Approve Job Service Retirement Application Calculation",
        "DISPLAY_NAME": "Approve Job Service Retirement Application Calculation"
      },
      {
        "ACTIVITY_ID": 50,
        "NAME": "Enter Payee Account Details",
        "DISPLAY_NAME": "Enter Payee Account Details"
      },
      {
        "ACTIVITY_ID": 51,
        "NAME": "Approve Payee Account",
        "DISPLAY_NAME": "Approve Payee Account"
      }
    ]
  },
  {
    "PROCESS_ID": 238,
    "DESCRIPTION": "Process DC Retirement Application",
    "name": "nfmProcessDCRetirementApplication",
    "Activities": [
      {
        "ACTIVITY_ID": 28,
        "NAME": "Enter DC Retirement Application Data",
        "DISPLAY_NAME": "Enter DC Retirement Application Data"
      },
      {
        "ACTIVITY_ID": 45,
        "NAME": "Audit DC Retirement Application Data",
        "DISPLAY_NAME": "Audit DC Retirement Application Data"
      },
      {
        "ACTIVITY_ID": 255,
        "NAME": "Approve Payee Account",
        "DISPLAY_NAME": "Approve Payee Account"
      },
      {
        "ACTIVITY_ID": 282,
        "NAME": "Audit & Approve DC Retirement Application Data",
        "DISPLAY_NAME": "Audit & Approve DC Retirement Application Data"
      }
    ]
  },
  {
    "PROCESS_ID": 239,
    "DESCRIPTION": "Process Disability Application",
    "name": "nfmProcessDisabilityApplication",
    "Activities": [
      {
        "ACTIVITY_ID": 31,
        "NAME": "Enter Disability Application Data",
        "DISPLAY_NAME": "Enter Disability Application Data"
      },
      {
        "ACTIVITY_ID": 46,
        "NAME": "Approve Disability Application Calculation",
        "DISPLAY_NAME": "Approve Disability Application Calculation"
      },
      {
        "ACTIVITY_ID": 47,
        "NAME": "Enter Payee Account Details",
        "DISPLAY_NAME": "Enter Payee Account Details"
      },
      {
        "ACTIVITY_ID": 48,
        "NAME": "Approve Payee Account",
        "DISPLAY_NAME": "Approve Payee Account"
      }
    ]
  },
  {
    "PROCESS_ID": 240,
    "DESCRIPTION": "Process Deferred Retirement Application",
    "name": "nfmProcessDeferredRetirementApplication",
    "Activities": [
      {
        "ACTIVITY_ID": 29,
        "NAME": "Enter Deferred Retirement Application Data",
        "DISPLAY_NAME": "Enter Deferred Retirement Application Data"
      }
    ]
  },
  {
    "PROCESS_ID": 241,
    "DESCRIPTION": "Process Deferred Vested Retirement Without Application",
    "name": "nfmProcessDeferredVestedRetirementWithoutApplication",
    "Activities": [
      {
        "ACTIVITY_ID": 30,
        "NAME": "Enter Deferred Vested Retirement Application",
        "DISPLAY_NAME": "Enter Deferred Vested Retirement Application"
      }
    ]
  },
  {
    "PROCESS_ID": 242,
    "DESCRIPTION": "Update ACH Information",
    "name": "nfmUpdateACHInformation",
    "Activities": [
      {
        "ACTIVITY_ID": 37,
        "NAME": "Review and Enter ACH information",
        "DISPLAY_NAME": "Review and Enter ACH Information"
      },
      {
        "ACTIVITY_ID": 38,
        "NAME": "Review and Approve ACH Information",
        "DISPLAY_NAME": "Review and Approve ACH Information"
      }
    ]
  },
  {
    "PROCESS_ID": 243,
    "DESCRIPTION": "Update Insurance ACH Information",
    "name": "nfmUpdateInsuranceACHInformation",
    "Activities": [
      {
        "ACTIVITY_ID": 39,
        "NAME": "Review and Enter Insurance ACH information",
        "DISPLAY_NAME": "Review and Enter Insurance ACH Information"
      },
      {
        "ACTIVITY_ID": 40,
        "NAME": "Review and Approve Insurance ACH Information",
        "DISPLAY_NAME": "Review and Approve Insurance ACH Information"
      }
    ]
  },
  {
    "PROCESS_ID": 244,
    "DESCRIPTION": "Update Rollover Instruction",
    "name": "nfmUpdateRolloverInstruction",
    "Activities": [
      {
        "ACTIVITY_ID": 41,
        "NAME": "Review and Enter Rollover Instruction",
        "DISPLAY_NAME": "Review and Enter Rollover Instruction"
      },
      {
        "ACTIVITY_ID": 42,
        "NAME": "Review and Approve Rollover Instruction",
        "DISPLAY_NAME": "Review and Approve Rollover Instruction"
      }
    ]
  },
  {
    "PROCESS_ID": 245,
    "DESCRIPTION": "Update Third Party RHIC Benefit Payment",
    "name": "nfmUpdateThirdPartyRHICBenefitPayment",
    "Activities": [
      {
        "ACTIVITY_ID": 43,
        "NAME": "Review and Enter RHIC Benefit Payment and Deductions",
        "DISPLAY_NAME": "Review and Enter RHIC Benefit Payment and Deductions"
      },
      {
        "ACTIVITY_ID": 44,
        "NAME": "Review and Approve RHIC Benefit Payment and Deductions",
        "DISPLAY_NAME": "Review and Approve RHIC Benefit Payment and Deductions"
      }
    ]
  },
  {
    "PROCESS_ID": 246,
    "DESCRIPTION": "Fulfill Pension RHIC Estimate Request",
    "name": "nfmFulfillPensionRHICEstimateRequest",
    "Activities": [
      {
        "ACTIVITY_ID": 52,
        "NAME": "Prepare Pension RHIC Estimate",
        "DISPLAY_NAME": "Prepare Pension RHIC Estimate"
      }
    ]
  },
  {
    "PROCESS_ID": 247,
    "DESCRIPTION": "Maintain RHIC Combining",
    "name": "nfmMaintainRHICCombining",
    "Activities": [
      {
        "ACTIVITY_ID": 53,
        "NAME": "Maintain RHIC",
        "DISPLAY_NAME": "Maintain RHIC"
      },
      {
        "ACTIVITY_ID": 54,
        "NAME": "Audit Maintain RHIC",
        "DISPLAY_NAME": "Audit Maintain RHIC"
      }
    ]
  },
  {
    "PROCESS_ID": 248,
    "DESCRIPTION": "Process Death Notification",
    "name": "nfmProcessDeathNotification",
    "Activities": [
      {
        "ACTIVITY_ID": 55,
        "NAME": "Certify Death Notification",
        "DISPLAY_NAME": "Certify Death Notification"
      },
      {
        "ACTIVITY_ID": 56,
        "NAME": "Complete Death Notification",
        "DISPLAY_NAME": "Complete Death Notification"
      },
      {
        "ACTIVITY_ID": 57,
        "NAME": "Enter Death Notification Data",
        "DISPLAY_NAME": "Enter Death Notification Data"
      }
    ]
  },
  {
    "PROCESS_ID": 249,
    "DESCRIPTION": "Process PreRetirement Death Benefit Application",
    "name": "nfmProcessPreRetirementDeathBenefitApplication",
    "Activities": [
      {
        "ACTIVITY_ID": 58,
        "NAME": "Enter PreRetirement Death Benefit Application Data",
        "DISPLAY_NAME": "Enter Pre-Retirement Death Benefit Application Data"
      },
      {
        "ACTIVITY_ID": 102,
        "NAME": "Approve PreRetirement Death Benefit Application",
        "DISPLAY_NAME": "Approve PreRetirement Death Benefit Application"
      },
      {
        "ACTIVITY_ID": 103,
        "NAME": "Enter Payee Account Details",
        "DISPLAY_NAME": "Enter Payee Account Details"
      },
      {
        "ACTIVITY_ID": 104,
        "NAME": "Approve Payee Account",
        "DISPLAY_NAME": "Approve Payee Account"
      }
    ]
  },
  {
    "PROCESS_ID": 250,
    "DESCRIPTION": "Process Beneficiary Auto Refund",
    "name": "nfmProcessBeneficiaryAutoRefund",
    "Activities": [
      {
        "ACTIVITY_ID": 59,
        "NAME": "Enter and Calculate Beneficiary Auto Refund",
        "DISPLAY_NAME": "Enter and Calculate Beneficiary Auto Refund"
      },
      {
        "ACTIVITY_ID": 60,
        "NAME": "Enter Payee Account Information",
        "DISPLAY_NAME": "Enter Payee Account Information"
      },
      {
        "ACTIVITY_ID": 61,
        "NAME": "Validate Application and Calculation",
        "DISPLAY_NAME": "Validate Application and Calculation"
      },
      {
        "ACTIVITY_ID": 62,
        "NAME": "Validate Payee Account",
        "DISPLAY_NAME": "Validate Payee Account"
      }
    ]
  },
  {
    "PROCESS_ID": 251,
    "DESCRIPTION": "Process Life Insurance Claims",
    "name": "nfmProcessLifeInsuranceClaims",
    "Activities": [
      {
        "ACTIVITY_ID": 63,
        "NAME": "Enter Insurance Check Data",
        "DISPLAY_NAME": "Enter Insurance Check Data"
      },
      {
        "ACTIVITY_ID": 64,
        "NAME": "Forward Life Insurance Claim",
        "DISPLAY_NAME": "Forward Life Insurance Claim"
      },
      {
        "ACTIVITY_ID": 337,
        "NAME": "Process Claim Received",
        "DISPLAY_NAME": "Process Claim Received"
      }
    ]
  },
  {
    "PROCESS_ID": 252,
    "DESCRIPTION": "Update Tax Withholding Information",
    "name": "nfmUpdateTaxWithholdingInformation",
    "Activities": [
      {
        "ACTIVITY_ID": 65,
        "NAME": "Review and Enter Tax Withholding Information",
        "DISPLAY_NAME": "Review and Enter Tax Withholding Information"
      },
      {
        "ACTIVITY_ID": 66,
        "NAME": "Review and Approve Tax Withholding Information",
        "DISPLAY_NAME": "Review and Approve Tax Withholding Information"
      }
    ]
  },
  {
    "PROCESS_ID": 253,
    "DESCRIPTION": "Update Tax Rate Table",
    "name": "nfmUpdateTaxRateTable",
    "Activities": [
      {
        "ACTIVITY_ID": 67,
        "NAME": "Review and Enter Tax Rates",
        "DISPLAY_NAME": "Review and Enter Tax Rates"
      },
      {
        "ACTIVITY_ID": 68,
        "NAME": "Review and Approve Tax Rates",
        "DISPLAY_NAME": "Review and Approve Tax Rates"
      }
    ]
  },
  {
    "PROCESS_ID": 254,
    "DESCRIPTION": "Update Deduction Information",
    "name": "nfmUpdateDeductionInformation",
    "Activities": [
      {
        "ACTIVITY_ID": 69,
        "NAME": "Review and Enter Deduction Information",
        "DISPLAY_NAME": "Review and Enter Deduction Information"
      },
      {
        "ACTIVITY_ID": 70,
        "NAME": "Review and Approve Deduction Information",
        "DISPLAY_NAME": "Review and Approve Deduction Information"
      }
    ]
  },
  {
    "PROCESS_ID": 255,
    "DESCRIPTION": "Update Third Party Health Insurance Deduction Information",
    "name": "nfmUpdateThirdPartyHealthInsuranceDeductionInformation",
    "Activities": [
      {
        "ACTIVITY_ID": 71,
        "NAME": "Review and Enter Third Party Health Deduction Information",
        "DISPLAY_NAME": "Review and Enter Third Party Health Deduction Information"
      },
      {
        "ACTIVITY_ID": 72,
        "NAME": "Review and Approve Third Party Health Deduction Information",
        "DISPLAY_NAME": "Review and Approve Third Party Health Deduction Information"
      }
    ]
  },
  {
    "PROCESS_ID": 256,
    "DESCRIPTION": "Process Refund Application and Calculation",
    "name": "nfmProcessRefundApplicationandCalculation",
    "Activities": [
      {
        "ACTIVITY_ID": 73,
        "NAME": "Enter Payee Account Information",
        "DISPLAY_NAME": "Enter Payee Account Information"
      },
      {
        "ACTIVITY_ID": 74,
        "NAME": "Review and Enter Refund Application Data",
        "DISPLAY_NAME": "Review and Enter Refund Application Data"
      },
      {
        "ACTIVITY_ID": 75,
        "NAME": "Validate Application and Calculation",
        "DISPLAY_NAME": "Validate Application and Calculation"
      },
      {
        "ACTIVITY_ID": 76,
        "NAME": "Validate Payee Account",
        "DISPLAY_NAME": "Validate Payee Account"
      }
    ]
  },
  {
    "PROCESS_ID": 257,
    "DESCRIPTION": "Process Remainder Refund",
    "name": "nfmProcessRemainderRefund",
    "Activities": [
      {
        "ACTIVITY_ID": 77,
        "NAME": "Enter and Calculate Remainder Refund",
        "DISPLAY_NAME": "Enter and Calculate Remainder Refund"
      },
      {
        "ACTIVITY_ID": 78,
        "NAME": "Validate and Approve Payee Account",
        "DISPLAY_NAME": "Validate and Approve Payee Account"
      }
    ]
  },
  {
    "PROCESS_ID": 258,
    "DESCRIPTION": "Process Auto Refund",
    "name": "nfmProcessAutoRefund",
    "Activities": [
      {
        "ACTIVITY_ID": 79,
        "NAME": "Enter and Calculate Auto Refund",
        "DISPLAY_NAME": "Enter and Calculate Auto Refund"
      },
      {
        "ACTIVITY_ID": 80,
        "NAME": "Enter Payee Account Information",
        "DISPLAY_NAME": "Enter Payee Account Information"
      },
      {
        "ACTIVITY_ID": 81,
        "NAME": "Validate Application and Calculation",
        "DISPLAY_NAME": "Validate Application and Calculation"
      },
      {
        "ACTIVITY_ID": 82,
        "NAME": "Validate Payee Account",
        "DISPLAY_NAME": "Validate Payee Account"
      }
    ]
  },
  {
    "PROCESS_ID": 259,
    "DESCRIPTION": "Process DB to DC Transfer",
    "name": "nfmProcessDBtoDCTransfer",
    "Activities": [
      {
        "ACTIVITY_ID": 83,
        "NAME": "Audit Prepare DC Transfer",
        "DISPLAY_NAME": "Audit Prepare DC Transfer"
      },
      {
        "ACTIVITY_ID": 84,
        "NAME": "Prepare DC Transfer",
        "DISPLAY_NAME": "Prepare DC Transfer"
      },
      {
        "ACTIVITY_ID": 85,
        "NAME": "Review Enrollment for DC Transfer",
        "DISPLAY_NAME": "Review Enrollment for DC Transfer"
      },
      {
        "ACTIVITY_ID": 251,
        "NAME": "Approve Payee Account",
        "DISPLAY_NAME": "Approve Payee Account"
      },
      {
        "ACTIVITY_ID": 355,
        "NAME": "Review Eligibility for DC Transfer",
        "DISPLAY_NAME": "Review Eligibility for DC Transfer"
      }
    ]
  },
  {
    "PROCESS_ID": 260,
    "DESCRIPTION": "Process DB to TIAA CREF Transfer",
    "name": "nfmProcessDBtoTIAACREFTransfer",
    "Activities": [
      {
        "ACTIVITY_ID": 86,
        "NAME": "Audit Prepare TIAA CREF Transfer",
        "DISPLAY_NAME": "Audit Prepare TIAA-CREF Transfer"
      },
      {
        "ACTIVITY_ID": 87,
        "NAME": "Prepare TIAA CREF Transfer",
        "DISPLAY_NAME": "Prepare TIAA-CREF Transfer"
      },
      {
        "ACTIVITY_ID": 88,
        "NAME": "Review Enrolment for TIAA CREF Transfer",
        "DISPLAY_NAME": "Review Enrolment for TIAA-CREF Transfer"
      },
      {
        "ACTIVITY_ID": 253,
        "NAME": "Approve Payee Account",
        "DISPLAY_NAME": "Approve Payee Account"
      }
    ]
  },
  {
    "PROCESS_ID": 261,
    "DESCRIPTION": "Process DB to TFFR Transfer",
    "name": "nfmProcessDBtoTFFRTransfer",
    "Activities": [
      {
        "ACTIVITY_ID": 89,
        "NAME": "Audit Prepare TFFR Transfer",
        "DISPLAY_NAME": "Audit Prepare TFFR Transfer"
      },
      {
        "ACTIVITY_ID": 90,
        "NAME": "Prepare TFFR Transfer",
        "DISPLAY_NAME": "Prepare TFFR Transfer"
      },
      {
        "ACTIVITY_ID": 91,
        "NAME": "Review Enrolment for TFFR Transfer",
        "DISPLAY_NAME": "Review Enrolment for TFFR Transfer"
      },
      {
        "ACTIVITY_ID": 252,
        "NAME": "Approve Payee Account",
        "DISPLAY_NAME": "Approve Payee Account"
      }
    ]
  },
  {
    "PROCESS_ID": 262,
    "DESCRIPTION": "Process Remainder Transfer",
    "name": "nfmProcessRemainderTransfer",
    "Activities": [
      {
        "ACTIVITY_ID": 92,
        "NAME": "Enter and Calculate Remainder Transfer",
        "DISPLAY_NAME": "Enter and Calculate Remainder Transfer"
      },
      {
        "ACTIVITY_ID": 93,
        "NAME": "Validate Application and Calculation",
        "DISPLAY_NAME": "Validate Application and Calculation"
      }
    ]
  },
  {
    "PROCESS_ID": 263,
    "DESCRIPTION": "Enter and Qualify DRO Application",
    "name": "nfmEnterandQualifyDROApplication",
    "Activities": [
      {
        "ACTIVITY_ID": 94,
        "NAME": "Enter DRO Application and Approve",
        "DISPLAY_NAME": "Enter DRO Application and Approve"
      },
      {
        "ACTIVITY_ID": 95,
        "NAME": "Audit DRO",
        "DISPLAY_NAME": "Audit DRO"
      }
    ]
  },
  {
    "PROCESS_ID": 264,
    "DESCRIPTION": "Nullify QDRO",
    "name": "nfmNullifyQDRO",
    "Activities": [
      {
        "ACTIVITY_ID": 96,
        "NAME": "Review Nullify QDRO",
        "DISPLAY_NAME": "Nullify QDRO"
      },
      {
        "ACTIVITY_ID": 97,
        "NAME": "Audit Nullification",
        "DISPLAY_NAME": "Audit Nullification"
      }
    ]
  },
  {
    "PROCESS_ID": 265,
    "DESCRIPTION": "Process QDRO Calculation",
    "name": "nfmProcessQDROCalculation",
    "Activities": [
      {
        "ACTIVITY_ID": 98,
        "NAME": "Approve QDRO Calculation",
        "DISPLAY_NAME": "Approve QDRO Calculation"
      },
      {
        "ACTIVITY_ID": 99,
        "NAME": "Enter Payee Account Information",
        "DISPLAY_NAME": "Enter Payee Account Information"
      },
      {
        "ACTIVITY_ID": 100,
        "NAME": "Review and Calculate Benefit Payment for QDRO",
        "DISPLAY_NAME": "Review and Calculate Benefit Payment for QDRO"
      },
      {
        "ACTIVITY_ID": 101,
        "NAME": "Validate Payee Account",
        "DISPLAY_NAME": "Validate Payee Account"
      }
    ]
  },
  {
    "PROCESS_ID": 266,
    "DESCRIPTION": "Process Death Match",
    "name": "nfmProcessDeathMatch",
    "Activities": [
      {
        "ACTIVITY_ID": 109,
        "NAME": "Research Death Notification",
        "DISPLAY_NAME": "Research Death Notification"
      }
    ]
  },
  {
    "PROCESS_ID": 267,
    "DESCRIPTION": "Process Disability to Normal Age Conversion",
    "name": "nfmProcessDisabilitytoNormalAgeConversion",
    "Activities": [
      {
        "ACTIVITY_ID": 105,
        "NAME": "Convert Disability to Normal",
        "DISPLAY_NAME": "Convert Disability to Normal"
      },
      {
        "ACTIVITY_ID": 106,
        "NAME": "Approve Disability to Normal calculation",
        "DISPLAY_NAME": "Approve Disability to Normal calculation"
      }
    ]
  },
  {
    "PROCESS_ID": 268,
    "DESCRIPTION": "Process Disability to Normal Rule Conversion",
    "name": "nfmProcessDisabilitytoNormalRuleConversion",
    "Activities": [
      {
        "ACTIVITY_ID": 107,
        "NAME": "Convert Disability to Normal",
        "DISPLAY_NAME": "Convert Disability to Normal"
      },
      {
        "ACTIVITY_ID": 108,
        "NAME": "Approve Disability to Normal calculation",
        "DISPLAY_NAME": "Approve Disability to Normal calculation"
      }
    ]
  },
  {
    "PROCESS_ID": 269,
    "DESCRIPTION": "Determine Financial Hardship",
    "name": "nfmDetermineFinancialHardship",
    "Activities": [
      {
        "ACTIVITY_ID": 110,
        "NAME": "Record Financial Hardship Decision",
        "DISPLAY_NAME": "Record Financial Hardship Decision"
      },
      {
        "ACTIVITY_ID": 111,
        "NAME": "Review Financial Hardship Application",
        "DISPLAY_NAME": "Review Financial Hardship Application"
      }
    ]
  },
  {
    "PROCESS_ID": 270,
    "DESCRIPTION": "Process Benefit Appeal",
    "name": "nfmProcessBenefitAppeal",
    "Activities": [
      {
        "ACTIVITY_ID": 112,
        "NAME": "Review Appeal Case Documents",
        "DISPLAY_NAME": "Review Appeal Case Documents"
      },
      {
        "ACTIVITY_ID": 113,
        "NAME": "Record Appeal Decision",
        "DISPLAY_NAME": "Record Appeal Decision"
      }
    ]
  },
  {
    "PROCESS_ID": 271,
    "DESCRIPTION": "Recertify Disability",
    "name": "nfmRecertifyDisability",
    "Activities": [
      {
        "ACTIVITY_ID": 114,
        "NAME": "Review Disability Recertification",
        "DISPLAY_NAME": "Review Disability Recertification"
      },
      {
        "ACTIVITY_ID": 115,
        "NAME": "Record Disability Recertification",
        "DISPLAY_NAME": "Record Disability Recertification"
      }
    ]
  },
  {
    "PROCESS_ID": 272,
    "DESCRIPTION": "Suspend Disability Benefits",
    "name": "nfmSuspendDisabilityBenefits",
    "Activities": [
      {
        "ACTIVITY_ID": 116,
        "NAME": "Review Suspension Disability Recertification",
        "DISPLAY_NAME": "Review Suspension Disability Recertification"
      }
    ]
  },
  {
    "PROCESS_ID": 273,
    "DESCRIPTION": "Verify Disability Income",
    "name": "nfmVerifyDisabilityIncome",
    "Activities": [
      {
        "ACTIVITY_ID": 117,
        "NAME": "Review Disability Income Forms",
        "DISPLAY_NAME": "Review Disability Income Forms"
      },
      {
        "ACTIVITY_ID": 118,
        "NAME": "Approve Disability Income Verification",
        "DISPLAY_NAME": "Approve Disability Income verification"
      }
    ]
  },
  {
    "PROCESS_ID": 274,
    "DESCRIPTION": "Recertify Pre 1991 Disability",
    "name": "nfmRecertifyPre1991Disability",
    "Activities": [
      {
        "ACTIVITY_ID": 119,
        "NAME": "Recertify Pre1991 Disability",
        "DISPLAY_NAME": "Receritify Pre 1991 Disability"
      },
      {
        "ACTIVITY_ID": 120,
        "NAME": "Record Disability Recertification",
        "DISPLAY_NAME": "Record Disability Recertification"
      }
    ]
  },
  {
    "PROCESS_ID": 275,
    "DESCRIPTION": "Process RMD",
    "name": "nfmProcessRMD",
    "Activities": [
      {
        "ACTIVITY_ID": 121,
        "NAME": "Generate RMD Notices",
        "DISPLAY_NAME": "Generate RMD Notices"
      },
      {
        "ACTIVITY_ID": 122,
        "NAME": "Enter Application",
        "DISPLAY_NAME": "Enter Application"
      },
      {
        "ACTIVITY_ID": 123,
        "NAME": "Approve Calculation",
        "DISPLAY_NAME": "Approve Calculation"
      },
      {
        "ACTIVITY_ID": 124,
        "NAME": "Enter Payee Account Details",
        "DISPLAY_NAME": "Enter Payee Account Details"
      },
      {
        "ACTIVITY_ID": 125,
        "NAME": "Audit Payee Account Details",
        "DISPLAY_NAME": "Audit Payee Account Details"
      }
    ]
  },
  {
    "PROCESS_ID": 276,
    "DESCRIPTION": "Remit Tax Withholding Amounts",
    "name": "nfmRemitTaxWithholdingAmounts",
    "Activities": [
      {
        "ACTIVITY_ID": 126,
        "NAME": "Remit Tax Withholding Amounts Activity",
        "DISPLAY_NAME": "Remit Tax Withholding Amounts"
      }
    ]
  },
  {
    "PROCESS_ID": 277,
    "DESCRIPTION": "Update SSN on Person Record",
    "name": "nfmUpdateSSNonPersonRecord",
    "Activities": [
      {
        "ACTIVITY_ID": 127,
        "NAME": "Update SSN",
        "DISPLAY_NAME": "Update SSN"
      },
      {
        "ACTIVITY_ID": 128,
        "NAME": "Generate corrected 1099R",
        "DISPLAY_NAME": "Generate corrected 1099R"
      },
      {
        "ACTIVITY_ID": 129,
        "NAME": "Correct FileNet data",
        "DISPLAY_NAME": "Correct FileNet data"
      }
    ]
  },
  {
    "PROCESS_ID": 278,
    "DESCRIPTION": "Split Person Record",
    "name": "nfmSplitPersonRecord",
    "Activities": [
      {
        "ACTIVITY_ID": 130,
        "NAME": "Create Person Record",
        "DISPLAY_NAME": "Create Person record"
      },
      {
        "ACTIVITY_ID": 131,
        "NAME": "Enter Adjustments",
        "DISPLAY_NAME": "Enter Adjustments"
      },
      {
        "ACTIVITY_ID": 132,
        "NAME": "Generate corrected 1099R",
        "DISPLAY_NAME": "Generate corrected 1099R"
      },
      {
        "ACTIVITY_ID": 133,
        "NAME": "Separate FileNet data",
        "DISPLAY_NAME": "Separate FileNet data"
      }
    ]
  },
  {
    "PROCESS_ID": 279,
    "DESCRIPTION": "Merge Person Record",
    "name": "nfmMergePersonRecord",
    "Activities": [
      {
        "ACTIVITY_ID": 134,
        "NAME": "Enter Adjustments",
        "DISPLAY_NAME": "Enter Adjustments"
      },
      {
        "ACTIVITY_ID": 135,
        "NAME": "Generate corrected 1099R",
        "DISPLAY_NAME": "Generate corrected 1099R"
      },
      {
        "ACTIVITY_ID": 136,
        "NAME": "Delete Person Record",
        "DISPLAY_NAME": "Delete Person record"
      },
      {
        "ACTIVITY_ID": 137,
        "NAME": "Merge FileNet data",
        "DISPLAY_NAME": "Merge FileNet data"
      }
    ]
  },
  {
    "PROCESS_ID": 280,
    "DESCRIPTION": "Suspend RTW Payee Account",
    "name": "nfmSuspendRTWPayeeAccount",
    "Activities": [
      {
        "ACTIVITY_ID": 138,
        "NAME": "SuspendRTWPayeeAccount",
        "DISPLAY_NAME": "SuspendRTWPayeeAccount"
      },
      {
        "ACTIVITY_ID": 139,
        "NAME": "Audit Suspension of RTW Payee Account",
        "DISPLAY_NAME": "Audit Suspension of RTW Payee Account"
      }
    ]
  },
  {
    "PROCESS_ID": 281,
    "DESCRIPTION": "Reverse RTW",
    "name": "nfmReverseRTW",
    "Activities": [
      {
        "ACTIVITY_ID": 140,
        "NAME": "Reverse RTW Re Enrollment",
        "DISPLAY_NAME": "Reverse RTW Re-enrollment"
      },
      {
        "ACTIVITY_ID": 141,
        "NAME": "Reverse Payee Account Suspension",
        "DISPLAY_NAME": "Reverse Payee Account Suspension"
      },
      {
        "ACTIVITY_ID": 142,
        "NAME": "Audit RTW Reversal",
        "DISPLAY_NAME": "Audit RTW Reversal"
      },
      {
        "ACTIVITY_ID": 143,
        "NAME": "Return RTW Contributions",
        "DISPLAY_NAME": "Return RTW Contributions"
      }
    ]
  },
  {
    "PROCESS_ID": 282,
    "DESCRIPTION": "Process Post Retirement Death Benefit Application",
    "name": "nfmProcessPostRetirementDeathBenefitApplication",
    "Activities": [
      {
        "ACTIVITY_ID": 144,
        "NAME": "Verify Post Retirement Death Benefit Application",
        "DISPLAY_NAME": "Verify Post Retirement Death Benefit Application"
      },
      {
        "ACTIVITY_ID": 145,
        "NAME": "Approve Calculation",
        "DISPLAY_NAME": "Approve Calculation"
      },
      {
        "ACTIVITY_ID": 146,
        "NAME": "Enter Payee Account Details",
        "DISPLAY_NAME": "Enter Payee Account Details"
      },
      {
        "ACTIVITY_ID": 147,
        "NAME": "Audit Payee Account Details",
        "DISPLAY_NAME": "Audit Payee Account Details"
      }
    ]
  },
  {
    "PROCESS_ID": 283,
    "DESCRIPTION": "Process Alternate Payee Post Retirement Death Benefit Application",
    "name": "nfmProcessAlternatePayeePostRetirementDeathBenefitApplication",
    "Activities": [
      {
        "ACTIVITY_ID": 148,
        "NAME": "Verify Annuitant Death Benefit Application",
        "DISPLAY_NAME": "Verify Annuitant Death Benefit Application"
      },
      {
        "ACTIVITY_ID": 149,
        "NAME": "Approve Calculation",
        "DISPLAY_NAME": "Approve Calculation"
      },
      {
        "ACTIVITY_ID": 150,
        "NAME": "Enter Payee Account Details",
        "DISPLAY_NAME": "Enter Payee Account Details"
      },
      {
        "ACTIVITY_ID": 151,
        "NAME": "Audit Payee Account Details",
        "DISPLAY_NAME": "Audit Payee Account Details"
      }
    ]
  },
  {
    "PROCESS_ID": 284,
    "DESCRIPTION": "Process First Beneficiary Death Benefit Application",
    "name": "nfmProcessFirstBeneficiaryDeathBenefitApplication",
    "Activities": [
      {
        "ACTIVITY_ID": 152,
        "NAME": "Verify First Beneficiary Death Benefit Application",
        "DISPLAY_NAME": "Verify First Beneficiary Death Benefit Application"
      },
      {
        "ACTIVITY_ID": 153,
        "NAME": "Approve Calculation",
        "DISPLAY_NAME": "Approve Calculation"
      },
      {
        "ACTIVITY_ID": 154,
        "NAME": "Enter Payee Account Details",
        "DISPLAY_NAME": "Enter Payee Account Details"
      },
      {
        "ACTIVITY_ID": 155,
        "NAME": "Audit Payee Account Details",
        "DISPLAY_NAME": "Audit Payee Account Details"
      }
    ]
  },
  {
    "PROCESS_ID": 285,
    "DESCRIPTION": "Change Payment Distribution Status",
    "name": "nfmProcessChangePaymentDistributionStatus",
    "Activities": [
      {
        "ACTIVITY_ID": 156,
        "NAME": "Payment History Distribution Status Change",
        "DISPLAY_NAME": "Change Payment Distribution Status"
      },
      {
        "ACTIVITY_ID": 157,
        "NAME": "Enter Rollover Instruction",
        "DISPLAY_NAME": "Enter Rollover Instruction"
      },
      {
        "ACTIVITY_ID": 158,
        "NAME": "Audit Distribution Status Change",
        "DISPLAY_NAME": "Audit Distribution Status Change"
      }
    ]
  },
  {
    "PROCESS_ID": 286,
    "DESCRIPTION": "Creating Receivable Against Payment History",
    "name": "nfmProcessCreatingReceivableAgainstPaymentHistory",
    "Activities": [
      {
        "ACTIVITY_ID": 159,
        "NAME": "Receivable Payment History Change",
        "DISPLAY_NAME": "Change Payment History"
      },
      {
        "ACTIVITY_ID": 160,
        "NAME": "Approve Receivable And Create Recovery",
        "DISPLAY_NAME": "Approve Receivable and Create Recovery"
      },
      {
        "ACTIVITY_ID": 161,
        "NAME": "Approve Recovery",
        "DISPLAY_NAME": "Approve Recovery"
      }
    ]
  },
  {
    "PROCESS_ID": 287,
    "DESCRIPTION": "Cancel Payment History",
    "name": "nfmProcessCancelPaymentHistory",
    "Activities": [
      {
        "ACTIVITY_ID": 162,
        "NAME": "Payment History Cancel",
        "DISPLAY_NAME": "Cancel Payment History"
      },
      {
        "ACTIVITY_ID": 163,
        "NAME": "Approve Cancellation",
        "DISPLAY_NAME": "Approve Cancellation"
      }
    ]
  },
  {
    "PROCESS_ID": 288,
    "DESCRIPTION": "Process Annual COLA",
    "name": "nfmProcessAnnualCOLA",
    "Activities": [
      {
        "ACTIVITY_ID": 166,
        "NAME": "Enter COLA Parameters",
        "DISPLAY_NAME": "Enter COLA Parameters"
      },
      {
        "ACTIVITY_ID": 167,
        "NAME": "Audit COLA Parameters",
        "DISPLAY_NAME": "Audit COLA Parameters"
      }
    ]
  },
  {
    "PROCESS_ID": 289,
    "DESCRIPTION": "Calculate Ad hoc Increase Or Supplemental Check",
    "name": "nfmCalculateAdhocIncreaseOrSupplementalCheck",
    "Activities": [
      {
        "ACTIVITY_ID": 164,
        "NAME": "Enter Ad hoc Or Supplemental Check Parameters",
        "DISPLAY_NAME": "Enter Ad hoc or Supplemental Check Parameters"
      },
      {
        "ACTIVITY_ID": 165,
        "NAME": "Audit Ad hoc Or Supplemental Check Parameters",
        "DISPLAY_NAME": "Audit Ad hoc or Supplemental Check Parameters"
      }
    ]
  },
  {
    "PROCESS_ID": 290,
    "DESCRIPTION": "Process Uncashed Benefit Checks",
    "name": "nfmProcessUncashedBenefitChecks",
    "Activities": [
      {
        "ACTIVITY_ID": 168,
        "NAME": "Research Uncashed Benefit Checks",
        "DISPLAY_NAME": "Research Uncashed Benefit Checks"
      },
      {
        "ACTIVITY_ID": 283,
        "NAME": "Reissue/Escheat Payment",
        "DISPLAY_NAME": "Reissue/Escheat Payment"
      },
      {
        "ACTIVITY_ID": 284,
        "NAME": "Approve Reissue/Escheat Payment",
        "DISPLAY_NAME": "Approve Reissue/Escheat Payment"
      }
    ]
  },
  {
    "PROCESS_ID": 291,
    "DESCRIPTION": "Create and Maintain Organization Information",
    "name": "nfmCreateandMaintainOrganizationInformation",
    "Activities": [
      {
        "ACTIVITY_ID": 169,
        "NAME": "Enter Organization Information",
        "DISPLAY_NAME": "Enter Organization Information"
      }
    ]
  },
  {
    "PROCESS_ID": 292,
    "DESCRIPTION": "Recalculate Pension and RHIC Benefit",
    "name": "nfmRecalculatePensionandRHICBenefit",
    "Activities": [
      {
        "ACTIVITY_ID": 170,
        "NAME": "Create Calculation",
        "DISPLAY_NAME": "Create Calculation"
      },
      {
        "ACTIVITY_ID": 171,
        "NAME": "Approve Calculation",
        "DISPLAY_NAME": "Approve Calculation"
      },
      {
        "ACTIVITY_ID": 172,
        "NAME": "Update Payee Account",
        "DISPLAY_NAME": "Update Payee Account"
      },
      {
        "ACTIVITY_ID": 173,
        "NAME": "Approve Payee Account",
        "DISPLAY_NAME": "Approve Payee Account"
      }
    ]
  },
  {
    "PROCESS_ID": 293,
    "DESCRIPTION": "Cancel Payee Account",
    "name": "nfmCancelPayeeAccount",
    "Activities": [
      {
        "ACTIVITY_ID": 174,
        "NAME": "CancelPending Payee Account",
        "DISPLAY_NAME": "Cancel Pending Payee Account"
      },
      {
        "ACTIVITY_ID": 175,
        "NAME": "Audit Payee Account",
        "DISPLAY_NAME": "Audit Payee Account"
      },
      {
        "ACTIVITY_ID": 176,
        "NAME": "Setup Receivable",
        "DISPLAY_NAME": "Setup Receivable"
      },
      {
        "ACTIVITY_ID": 177,
        "NAME": "Approve Recovery",
        "DISPLAY_NAME": "Approve Recovery"
      }
    ]
  },
  {
    "PROCESS_ID": 294,
    "DESCRIPTION": "Popup Payee Account",
    "name": "nfmPopupPayeeAccount",
    "Activities": [
      {
        "ACTIVITY_ID": 178,
        "NAME": "Review Payee Account",
        "DISPLAY_NAME": "Review Payee Account"
      },
      {
        "ACTIVITY_ID": 179,
        "NAME": "Audit Payee Account",
        "DISPLAY_NAME": "Audit Payee Account"
      }
    ]
  },
  {
    "PROCESS_ID": 295,
    "DESCRIPTION": "Reactivate Payee Account",
    "name": "nfmReactivatePayeeAccount",
    "Activities": [
      {
        "ACTIVITY_ID": 180,
        "NAME": "Review Payee Account",
        "DISPLAY_NAME": "Review Payee Account"
      },
      {
        "ACTIVITY_ID": 181,
        "NAME": "Audit Payee Account",
        "DISPLAY_NAME": "Audit Payee Account"
      }
    ]
  },
  {
    "PROCESS_ID": 296,
    "DESCRIPTION": "Update Payment Option",
    "name": "nfmUpdatePaymentOption",
    "Activities": [
      {
        "ACTIVITY_ID": 182,
        "NAME": "Review Payment Option Recovery",
        "DISPLAY_NAME": "Review Payment Option Recovery"
      },
      {
        "ACTIVITY_ID": 183,
        "NAME": "Audit Payment Option Recovery",
        "DISPLAY_NAME": "Audit Payment Option Recovery"
      }
    ]
  },
  {
    "PROCESS_ID": 297,
    "DESCRIPTION": "Update Dues Rate Table",
    "name": "nfmUpdateDuesRateTable",
    "Activities": [
      {
        "ACTIVITY_ID": 189,
        "NAME": "Review and Enter Dues Rates",
        "DISPLAY_NAME": "Review and Enter Dues Rates"
      },
      {
        "ACTIVITY_ID": 190,
        "NAME": "Review and Approve Dues Rates",
        "DISPLAY_NAME": "Review and Approve Dues Rates"
      }
    ]
  },
  {
    "PROCESS_ID": 298,
    "DESCRIPTION": "ACH Pull For Retirement",
    "name": "nfmACHPullForRetirement",
    "Activities": [
      {
        "ACTIVITY_ID": 191,
        "NAME": "Debit ACH Information for Retirement",
        "DISPLAY_NAME": "Debit ACH Information for Retirement"
      },
      {
        "ACTIVITY_ID": 192,
        "NAME": "Move ACH File to BND",
        "DISPLAY_NAME": "Move ACH File to BND"
      }
    ]
  },
  {
    "PROCESS_ID": 299,
    "DESCRIPTION": "ACH Pull For Deferred Compensation",
    "name": "nfmACHPullForDeferredCompensation",
    "Activities": [
      {
        "ACTIVITY_ID": 193,
        "NAME": "Debit ACH Information for Deferred Compensation",
        "DISPLAY_NAME": "Debit ACH Information for Deferred Compensation"
      },
      {
        "ACTIVITY_ID": 194,
        "NAME": "Move Deferred Compensation ACH File to BND",
        "DISPLAY_NAME": "Move Deferred Compensation ACH File to BND"
      }
    ]
  },
  {
    "PROCESS_ID": 300,
    "DESCRIPTION": "ACH Pull For IBS Insurance",
    "name": "nfmACHPullForIBSInsurance",
    "Activities": [
      {
        "ACTIVITY_ID": 195,
        "NAME": "Debit ACH Information for IBS Insurance",
        "DISPLAY_NAME": "Debit ACH Information for IBS Insurance"
      },
      {
        "ACTIVITY_ID": 196,
        "NAME": "Move IBS Insurance ACH File to BND",
        "DISPLAY_NAME": "Move IBS Insurance ACH File to BND"
      }
    ]
  },
  {
    "PROCESS_ID": 301,
    "DESCRIPTION": "ACH Pull For Insurance",
    "name": "nfmACHPullForInsurance",
    "Activities": [
      {
        "ACTIVITY_ID": 197,
        "NAME": "Debit ACH Information for Insurance",
        "DISPLAY_NAME": "Debit ACH Information for Insurance"
      },
      {
        "ACTIVITY_ID": 198,
        "NAME": "Move Insurance ACH File to BND",
        "DISPLAY_NAME": "Move Insurance ACH File to BND"
      }
    ]
  },
  {
    "PROCESS_ID": 302,
    "DESCRIPTION": "Process Online Contact Ticket",
    "name": "nfmProcessOnlineContactTicket",
    "Activities": [
      {
        "ACTIVITY_ID": 199,
        "NAME": "Process Online Contact Ticket",
        "DISPLAY_NAME": "Process Online Contact Ticket"
      }
    ]
  },
  {
    "PROCESS_ID": 303,
    "DESCRIPTION": "Process Online Benefit Estimate Request",
    "name": "nfmProcessOnlineBenefitEstimateRequest",
    "Activities": [
      {
        "ACTIVITY_ID": 200,
        "NAME": "Process Online Benefit Estimate Request",
        "DISPLAY_NAME": "Process Online Benefit Estimate Request"
      }
    ]
  },
  {
    "PROCESS_ID": 304,
    "DESCRIPTION": "Process Online Service Purchase Request",
    "name": "nfmProcessOnlineServicePurchaseRequest",
    "Activities": [
      {
        "ACTIVITY_ID": 201,
        "NAME": "Process Online Service Purchase Request",
        "DISPLAY_NAME": "Process Online Service Purchase Request"
      },
      {
        "ACTIVITY_ID": 295,
        "NAME": "Audit Prepare Cost Statement",
        "DISPLAY_NAME": "Audit Prepare Cost Statement"
      },
      {
        "ACTIVITY_ID": 296,
        "NAME": "Generate Service Credit Purchase Letter",
        "DISPLAY_NAME": "Generate Service Credit Purchase Letter"
      }
    ]
  },
  {
    "PROCESS_ID": 305,
    "DESCRIPTION": "Process Seminar IDB",
    "name": "nfmProcessSeminarIDB",
    "Activities": [
      {
        "ACTIVITY_ID": 202,
        "NAME": "Process IDB Remittance",
        "DISPLAY_NAME": "Process IDB Remittance"
      }
    ]
  },
  {
    "PROCESS_ID": 306,
    "DESCRIPTION": "WSS Enroll in Pension and Insurance Plans",
    "name": "nfmWSSEnrollNewHireinPensionandInsurancePlans",
    "Activities": [
      {
        "ACTIVITY_ID": 203,
        "NAME": "Enter Plan Enrollment Data",
        "DISPLAY_NAME": "Enter Plan Enrollment Data"
      },
      {
        "ACTIVITY_ID": 204,
        "NAME": "Audit Plan Enrollment Data",
        "DISPLAY_NAME": "Audit Plan Enrollment Data"
      }
    ]
  },
  {
    "PROCESS_ID": 307,
    "DESCRIPTION": "Process IBS Remittance Billing",
    "name": "nfmProcessIBSRemittanceBilling",
    "Activities": [
      {
        "ACTIVITY_ID": 205,
        "NAME": "Apply Remittance to IBS Billing",
        "DISPLAY_NAME": "Apply Remittance to IBS Billing"
      }
    ]
  },
  {
    "PROCESS_ID": 308,
    "DESCRIPTION": "Process Journal Entry",
    "name": "nfmProcessJournalEntry",
    "Activities": [
      {
        "ACTIVITY_ID": 206,
        "NAME": "Enter Journal Data",
        "DISPLAY_NAME": "Enter Journal Data"
      },
      {
        "ACTIVITY_ID": 207,
        "NAME": "Post Journal Data",
        "DISPLAY_NAME": "Post Journal Data"
      }
    ]
  },
  {
    "PROCESS_ID": 309,
    "DESCRIPTION": "Review Employer Payroll Report",
    "name": "nfmReviewEmployerPayrollReport",
    "Activities": [
      {
        "ACTIVITY_ID": 208,
        "NAME": "Review the Payroll Report",
        "DISPLAY_NAME": "Review the Payroll Report"
      }
    ]
  },
  {
    "PROCESS_ID": 310,
    "DESCRIPTION": "MSS Schedule Appointment",
    "name": "nfmMSSScheduleAppointment",
    "Activities": [
      {
        "ACTIVITY_ID": 209,
        "NAME": "Conduct Appointment",
        "DISPLAY_NAME": "Conduct Appointment"
      }
    ]
  },
  {
    "PROCESS_ID": 311,
    "DESCRIPTION": "ESS Schedule Appointment",
    "name": "nfmESSScheduleAppointment",
    "Activities": [
      {
        "ACTIVITY_ID": 210,
        "NAME": "Conduct Appointment",
        "DISPLAY_NAME": "Conduct Appointment"
      }
    ]
  },
  {
    "PROCESS_ID": 312,
    "DESCRIPTION": "Process WSS Death Notification",
    "name": "nfmProcessWSSDeathNotification",
    "Activities": [
      {
        "ACTIVITY_ID": 211,
        "NAME": "Enter Death Notification Data",
        "DISPLAY_NAME": "Enter Death Notification Data"
      },
      {
        "ACTIVITY_ID": 212,
        "NAME": "Certify Death Notification",
        "DISPLAY_NAME": "Certify Death Notification"
      },
      {
        "ACTIVITY_ID": 213,
        "NAME": "Complete Death Notification",
        "DISPLAY_NAME": "Complete Death Notification"
      }
    ]
  },
  {
    "PROCESS_ID": 313,
    "DESCRIPTION": "Employment Change Request",
    "name": "nfmEmploymentChangeRequest",
    "Activities": [
      {
        "ACTIVITY_ID": 219,
        "NAME": "Process Person Employment Change Request",
        "DISPLAY_NAME": "Process Person Employment Change Request"
      },
      {
        "ACTIVITY_ID": 220,
        "NAME": "Audit Member Employment Information",
        "DISPLAY_NAME": "Audit Member Employment Information"
      }
    ]
  },
  {
    "PROCESS_ID": 314,
    "DESCRIPTION": "Member Record Request",
    "name": "nfmMemberRecordRequest",
    "Activities": [
      {
        "ACTIVITY_ID": 216,
        "NAME": "Process Member Record Request",
        "DISPLAY_NAME": "Process Member Record Request"
      },
      {
        "ACTIVITY_ID": 217,
        "NAME": "Audit Member Information",
        "DISPLAY_NAME": "Audit Member Information"
      }
    ]
  },
  {
    "PROCESS_ID": 315,
    "DESCRIPTION": "Process IBS Adjustment",
    "name": "nfmProcessIBSAdjustment",
    "Activities": [
      {
        "ACTIVITY_ID": 221,
        "NAME": "Setup IBS Adjustment",
        "DISPLAY_NAME": "Setup IBS Adjustment"
      },
      {
        "ACTIVITY_ID": 222,
        "NAME": "Audit Election",
        "DISPLAY_NAME": "Audit Election"
      }
    ]
  },
  {
    "PROCESS_ID": 316,
    "DESCRIPTION": "Process IBS Adjustment Header",
    "name": "nfmProcessIBSAdjustmentHeader",
    "Activities": [
      {
        "ACTIVITY_ID": 223,
        "NAME": "Approve IBS Adjustment header",
        "DISPLAY_NAME": "Approve IBS Adjustment header"
      }
    ]
  },
  {
    "PROCESS_ID": 317,
    "DESCRIPTION": "Process Notice Of Employment Change",
    "name": "nfmProcessNoticeOfEmploymentChange",
    "Activities": [
      {
        "ACTIVITY_ID": 224,
        "NAME": "Maintain Employment Change",
        "DISPLAY_NAME": "Maintain Employment Change"
      },
      {
        "ACTIVITY_ID": 225,
        "NAME": "Audit Employment Change",
        "DISPLAY_NAME": "Audit Employment Change"
      }
    ]
  },
  {
    "PROCESS_ID": 318,
    "DESCRIPTION": "Process Audit Insurance Claims",
    "name": "nfmProcessAuditInsuranceClaims",
    "Activities": [
      {
        "ACTIVITY_ID": 226,
        "NAME": "Audit Insurance Claims",
        "DISPLAY_NAME": "Audit Insurance Claims"
      }
    ]
  },
  {
    "PROCESS_ID": 319,
    "DESCRIPTION": "Process Counseling Correspondence",
    "name": "nfmProcessCounselingCorrespondence",
    "Activities": [
      {
        "ACTIVITY_ID": 227,
        "NAME": "Counseling Correspondence",
        "DISPLAY_NAME": "Counseling Correspondence"
      }
    ]
  },
  {
    "PROCESS_ID": 320,
    "DESCRIPTION": "Process Create New Organization",
    "name": "nfmProcessCreateNewOrganization",
    "Activities": [
      {
        "ACTIVITY_ID": 228,
        "NAME": "Create New Organization",
        "DISPLAY_NAME": "Create New Organization"
      }
    ]
  },
  {
    "PROCESS_ID": 321,
    "DESCRIPTION": "Process Fulfill Member Request",
    "name": "nfmProcessFulfillMemberRequest",
    "Activities": [
      {
        "ACTIVITY_ID": 229,
        "NAME": "Fulfill Member Request",
        "DISPLAY_NAME": "Fulfill Member Request"
      }
    ]
  },
  {
    "PROCESS_ID": 322,
    "DESCRIPTION": "Process Internal Auditor Correspondence",
    "name": "nfmProcessInternalAuditorCorrespondence",
    "Activities": [
      {
        "ACTIVITY_ID": 230,
        "NAME": "Internal Auditor Correspondence",
        "DISPLAY_NAME": "Internal Auditor Correspondence"
      }
    ]
  },
  {
    "PROCESS_ID": 323,
    "DESCRIPTION": "Process Correspondence",
    "name": "nfmProcessCorrespondence",
    "Activities": [
      {
        "ACTIVITY_ID": 231,
        "NAME": "Process Correspondence for Member",
        "DISPLAY_NAME": "Process Correspondence for Member"
      }
    ]
  },
  {
    "PROCESS_ID": 324,
    "DESCRIPTION": "Process Dual Membership",
    "name": "nfmProcessDualMembership",
    "Activities": [
      {
        "ACTIVITY_ID": 232,
        "NAME": "Dual Membership",
        "DISPLAY_NAME": "Dual Membership"
      }
    ]
  },
  {
    "PROCESS_ID": 325,
    "DESCRIPTION": "Process Request for PHI",
    "name": "nfmProcessRequestForPHI",
    "Activities": [
      {
        "ACTIVITY_ID": 233,
        "NAME": "Request for PHI",
        "DISPLAY_NAME": "Request for PHI"
      }
    ]
  },
  {
    "PROCESS_ID": 326,
    "DESCRIPTION": "Process Verify Pension Income and Insurance Premiums",
    "name": "nfmProcessVerifyPensionIncomeAndInsurancePremiums",
    "Activities": [
      {
        "ACTIVITY_ID": 234,
        "NAME": "Pension Income and Insurance Premiums",
        "DISPLAY_NAME": "Pension Income and Insurance Premiums"
      }
    ]
  },
  {
    "PROCESS_ID": 327,
    "DESCRIPTION": "Process Wellness Benefit Program",
    "name": "nfmProcessWellnessBenefitProgram",
    "Activities": [
      {
        "ACTIVITY_ID": 235,
        "NAME": "Process Wellness Form",
        "DISPLAY_NAME": "Process Wellness Form"
      }
    ]
  },
  {
    "PROCESS_ID": 328,
    "DESCRIPTION": "Process Maintain Deferred Comp Plan",
    "name": "nfmProcessMaintainDeferredCompPlan",
    "Activities": [
      {
        "ACTIVITY_ID": 236,
        "NAME": "Maintain Deferred Comp Plan",
        "DISPLAY_NAME": "Maintain Deferred Comp Plan"
      },
      {
        "ACTIVITY_ID": 237,
        "NAME": "Audit Deferred Comp Maintenance",
        "DISPLAY_NAME": "Audit Deferred Comp Maintenance"
      }
    ]
  },
  {
    "PROCESS_ID": 329,
    "DESCRIPTION": "Process Maintain Flex Comp Plan",
    "name": "nfmProcessMaintainFlexCompPlan",
    "Activities": [
      {
        "ACTIVITY_ID": 238,
        "NAME": "Maintain Flex Comp Plan",
        "DISPLAY_NAME": "Maintain Flex Comp Plan"
      },
      {
        "ACTIVITY_ID": 239,
        "NAME": "Audit Flex Comp Plan",
        "DISPLAY_NAME": "Audit Flex Comp Plan"
      }
    ]
  },
  {
    "PROCESS_ID": 330,
    "DESCRIPTION": "Process Maintain Insurance Plan",
    "name": "nfmProcessMaintainInsurancePlan",
    "Activities": [
      {
        "ACTIVITY_ID": 240,
        "NAME": "Maintain Insurance Plan",
        "DISPLAY_NAME": "Maintain Insurance Plan"
      },
      {
        "ACTIVITY_ID": 241,
        "NAME": "Audit Insurance Plan",
        "DISPLAY_NAME": "Audit Insurance Plan"
      }
    ]
  },
  {
    "PROCESS_ID": 331,
    "DESCRIPTION": "Process Maintain Person Information",
    "name": "nfmProcessMaintainPersonInformation",
    "Activities": [
      {
        "ACTIVITY_ID": 242,
        "NAME": "Maintain Person Information",
        "DISPLAY_NAME": "Maintain Person Information"
      },
      {
        "ACTIVITY_ID": 243,
        "NAME": "Audit Person Information",
        "DISPLAY_NAME": "Audit Person Information"
      }
    ]
  },
  {
    "PROCESS_ID": 332,
    "DESCRIPTION": "Process Update Flex Comp Plan",
    "name": "nfmProcessUpdateFlexCompPlan",
    "Activities": [
      {
        "ACTIVITY_ID": 244,
        "NAME": "Update Flex Comp Plan",
        "DISPLAY_NAME": "Update Flex Comp Plan"
      },
      {
        "ACTIVITY_ID": 245,
        "NAME": "Verify Flex Comp Plan",
        "DISPLAY_NAME": "Verify Flex Comp Plan"
      },
      {
        "ACTIVITY_ID": 246,
        "NAME": "Audit Flex Comp Plan",
        "DISPLAY_NAME": "Audit Flex Comp Plan"
      }
    ]
  },
  {
    "PROCESS_ID": 333,
    "DESCRIPTION": "ESS Deferred Comp Problem",
    "name": "nfmProcessESSDeferredCompProblem",
    "Activities": [
      {
        "ACTIVITY_ID": 247,
        "NAME": "ESS Problem Resolution",
        "DISPLAY_NAME": "ESS Problem Resolution"
      }
    ]
  },
  {
    "PROCESS_ID": 334,
    "DESCRIPTION": "ESS Insurance Problem",
    "name": "nfmProcessESSInsuranceProblem",
    "Activities": [
      {
        "ACTIVITY_ID": 248,
        "NAME": "ESS Problem Resolution",
        "DISPLAY_NAME": "ESS Problem Resolution"
      }
    ]
  },
  {
    "PROCESS_ID": 335,
    "DESCRIPTION": "ESS Other Problem",
    "name": "nfmProcessESSOtherProblem",
    "Activities": [
      {
        "ACTIVITY_ID": 249,
        "NAME": "ESS Problem Resolution",
        "DISPLAY_NAME": "ESS Problem Resolution"
      }
    ]
  },
  {
    "PROCESS_ID": 336,
    "DESCRIPTION": "ESS Retirement Problem",
    "name": "nfmProcessESSRetirementProblem",
    "Activities": [
      {
        "ACTIVITY_ID": 250,
        "NAME": "ESS Problem Resolution",
        "DISPLAY_NAME": "ESS Problem Resolution"
      }
    ]
  },
  {
    "PROCESS_ID": 337,
    "DESCRIPTION": "Resolve Incoming Mail",
    "name": "nfmResolveIncomingMail",
    "Activities": [
      {
        "ACTIVITY_ID": 254,
        "NAME": "Resolve Incoming Mail",
        "DISPLAY_NAME": "Resolve Incoming Mail"
      }
    ]
  },
  {
    "PROCESS_ID": 338,
    "DESCRIPTION": "Flexcomp Annual Enrollment",
    "name": "nfmFlexCompAnnualEnrollment",
    "Activities": [
      {
        "ACTIVITY_ID": 256,
        "NAME": "Process Flexcomp Annual Enrollment",
        "DISPLAY_NAME": "Process Flexcomp Annual Enrollment"
      },
      {
        "ACTIVITY_ID": 257,
        "NAME": "Audit Flex Comp Plan",
        "DISPLAY_NAME": "Audit Flex Comp Plan"
      }
    ]
  },
  {
    "PROCESS_ID": 339,
    "DESCRIPTION": "D/V Annual Enrollment",
    "name": "nfmDVAnnualEnrollment",
    "Activities": [
      {
        "ACTIVITY_ID": 258,
        "NAME": "Process D/V Annual Enrollment",
        "DISPLAY_NAME": "Process D/V Annual Enrollment"
      },
      {
        "ACTIVITY_ID": 259,
        "NAME": "Audit D/V Annual Enrollment",
        "DISPLAY_NAME": "Audit D/V Annual Enrollment"
      }
    ]
  },
  {
    "PROCESS_ID": 340,
    "DESCRIPTION": "Life Insurance Annual Enrollment",
    "name": "nfmLifeInsuranceAnnualEnrollment",
    "Activities": [
      {
        "ACTIVITY_ID": 260,
        "NAME": "Process Life Insurance Annual Enrollment",
        "DISPLAY_NAME": "Process Life Insurance Annual Enrollment"
      },
      {
        "ACTIVITY_ID": 261,
        "NAME": "Audit Life Annual Enrollment",
        "DISPLAY_NAME": "Audit Life Annual Enrollment"
      }
    ]
  },
  {
    "PROCESS_ID": 341,
    "DESCRIPTION": "Process IBS Payment Election Adjustment",
    "name": "nfmProcessIBSPaymentElectionAdjustment",
    "Activities": [
      {
        "ACTIVITY_ID": 262,
        "NAME": "IBS Payment Election Adjustment",
        "DISPLAY_NAME": "IBS Payment Election Adjustment"
      }
    ]
  },
  {
    "PROCESS_ID": 343,
    "DESCRIPTION": "Employer Payment Plan Special Election",
    "name": "nfmEmployerPaymentPlanSpecialElection",
    "Activities": [
      {
        "ACTIVITY_ID": 264,
        "NAME": "Review Employer Payment Election",
        "DISPLAY_NAME": "Review Employer Payment Election"
      },
      {
        "ACTIVITY_ID": 265,
        "NAME": "Update Employer Payment Election",
        "DISPLAY_NAME": "Update Employer Payment Election"
      }
    ]
  },
  {
    "PROCESS_ID": 344,
    "DESCRIPTION": "Process Notice Of Transfer",
    "name": "nfmProcessNoticeOfTransfer",
    "Activities": [
      {
        "ACTIVITY_ID": 266,
        "NAME": "Process Notice of Transfer",
        "DISPLAY_NAME": "Process Notice of Transfer"
      },
      {
        "ACTIVITY_ID": 267,
        "NAME": "Audit Notice of Transfer",
        "DISPLAY_NAME": "Audit Notice of Transfer"
      }
    ]
  },
  {
    "PROCESS_ID": 345,
    "DESCRIPTION": "Health AnnualEnrollment",
    "name": "nfmHealthAnnualEnrollment",
    "Activities": [
      {
        "ACTIVITY_ID": 270,
        "NAME": "Process Health Annual Enrollment",
        "DISPLAY_NAME": "Process Health Annual Enrollment"
      },
      {
        "ACTIVITY_ID": 271,
        "NAME": "Audit Health Annual Enrollment",
        "DISPLAY_NAME": "Audit Health Annual Enrollment"
      }
    ]
  },
  {
    "PROCESS_ID": 347,
    "DESCRIPTION": "Process Evidence of Insurability",
    "name": "nfmProcessEvidenceofInsurability",
    "Activities": [
      {
        "ACTIVITY_ID": 273,
        "NAME": "Maintain Insurance Plan",
        "DISPLAY_NAME": "Maintain Insurance Plan"
      },
      {
        "ACTIVITY_ID": 274,
        "NAME": "Audit Insurance Plan",
        "DISPLAY_NAME": "Audit Insurance Plan"
      }
    ]
  },
  {
    "PROCESS_ID": 348,
    "DESCRIPTION": "MSS HDV Annual Enrollment",
    "name": "nfmMSSHDVAnnualEnrollment",
    "Activities": [
      {
        "ACTIVITY_ID": 275,
        "NAME": "Enter Plan Enrollment Data",
        "DISPLAY_NAME": "Enter Plan Enrollment Data"
      }
    ]
  },
  {
    "PROCESS_ID": 349,
    "DESCRIPTION": "MSS Flex comp Annual Enrollment",
    "name": "nfmMSSFlexcompAnnualEnrollment",
    "Activities": [
      {
        "ACTIVITY_ID": 276,
        "NAME": "Enter Plan Enrollment Data",
        "DISPLAY_NAME": "Enter Plan Enrollment Data"
      }
    ]
  },
  {
    "PROCESS_ID": 350,
    "DESCRIPTION": "MSS Life Insurance Annual Enrollment",
    "name": "nfmMSSLifeInsuranceAnnualEnrollment",
    "Activities": [
      {
        "ACTIVITY_ID": 277,
        "NAME": "Enter Plan Enrollment Data",
        "DISPLAY_NAME": "Enter Plan Enrollment Data"
      }
    ]
  },
  {
    "PROCESS_ID": 351,
    "DESCRIPTION": "WSSProcessUpdateFlexCompPlan",
    "name": "nfmWSSProcessUpdateFlexCompPlan",
    "Activities": [
      {
        "ACTIVITY_ID": 278,
        "NAME": "Update Flex Comp Plan",
        "DISPLAY_NAME": "Update Flex Comp Plan"
      },
      {
        "ACTIVITY_ID": 279,
        "NAME": "Verify Flex Comp Plan",
        "DISPLAY_NAME": "Verify Flex Comp Plan"
      }
    ]
  },
  {
    "PROCESS_ID": 352,
    "DESCRIPTION": "Popup RHICAmount",
    "name": "nfmPopupRHICAmount",
    "Activities": [
      {
        "ACTIVITY_ID": 280,
        "NAME": "Review RHIC Amount",
        "DISPLAY_NAME": "Review RHIC Amount"
      },
      {
        "ACTIVITY_ID": 281,
        "NAME": "Audit RHIC Amount",
        "DISPLAY_NAME": "Audit RHIC Amount"
      }
    ]
  },
  {
    "PROCESS_ID": 353,
    "DESCRIPTION": "Return Mail Processing",
    "name": "nfmReturnMailProcessing",
    "Activities": [
      {
        "ACTIVITY_ID": 285,
        "NAME": "Return Mail Processing",
        "DISPLAY_NAME": "Return Mail Processing"
      }
    ]
  },
  {
    "PROCESS_ID": 354,
    "DESCRIPTION": "Process Remainder Refund/Transfer",
    "name": "nfmProcessRemainderTransferRefund",
    "Activities": [
      {
        "ACTIVITY_ID": 286,
        "NAME": "Create Calculation",
        "DISPLAY_NAME": "Create Calculation"
      },
      {
        "ACTIVITY_ID": 287,
        "NAME": "Approve Calculation",
        "DISPLAY_NAME": "Approve Calculation"
      },
      {
        "ACTIVITY_ID": 288,
        "NAME": "Update Payee Account",
        "DISPLAY_NAME": "Update Payee Account"
      },
      {
        "ACTIVITY_ID": 289,
        "NAME": "Approve Payee Account",
        "DISPLAY_NAME": "Approve Payee Account"
      }
    ]
  },
  {
    "PROCESS_ID": 355,
    "DESCRIPTION": "Update Payment Selection Option",
    "name": "nfmUpdatePaymentSelectionOption",
    "Activities": [
      {
        "ACTIVITY_ID": 290,
        "NAME": "Update Payment Selection Option",
        "DISPLAY_NAME": "Update Payment Selection Option"
      }
    ]
  },
  {
    "PROCESS_ID": 356,
    "DESCRIPTION": "Fulfill Service Credit Purchase Query - Unused Sick Leave",
    "name": "nfmFulfillServiceCreditPurchaseQueryUnusedSickLeaves",
    "Activities": [
      {
        "ACTIVITY_ID": 291,
        "NAME": "Prepare Cost Statement",
        "DISPLAY_NAME": "Prepare Cost Statement"
      },
      {
        "ACTIVITY_ID": 292,
        "NAME": "Audit Prepare Cost Statement",
        "DISPLAY_NAME": "Audit Prepare Cost Statement"
      },
      {
        "ACTIVITY_ID": 293,
        "NAME": "Generate Service Credit Purchase Letter",
        "DISPLAY_NAME": "Generate Service Credit Purchase Letter"
      }
    ]
  },
  {
    "PROCESS_ID": 357,
    "DESCRIPTION": "Service Purchase Payment Installments Termination",
    "name": "nfmServicePurchasePaymentInstallmentsTermination",
    "Activities": [
      {
        "ACTIVITY_ID": 294,
        "NAME": "Service Purchase Payment Installments Termination",
        "DISPLAY_NAME": "Service Purchase Payment Installments Termination"
      }
    ]
  },
  {
    "PROCESS_ID": 358,
    "DESCRIPTION": "Maintain RHIC Uncombined",
    "name": "nfmMaintainRHICUncombined",
    "Activities": [
      {
        "ACTIVITY_ID": 297,
        "NAME": "Maintain RHIC",
        "DISPLAY_NAME": "Maintain RHIC"
      },
      {
        "ACTIVITY_ID": 298,
        "NAME": "Audit Maintain RHIC",
        "DISPLAY_NAME": "Audit Maintain RHIC"
      }
    ]
  },
  {
    "PROCESS_ID": 359,
    "DESCRIPTION": "Suspend Benefits  Uncashed Checks",
    "name": "nfmSuspendBenefitsUncashedChecks",
    "Activities": [
      {
        "ACTIVITY_ID": 299,
        "NAME": "Suspend Payee Account",
        "DISPLAY_NAME": "Suspend Payee Account"
      },
      {
        "ACTIVITY_ID": 300,
        "NAME": "Audit suspended Payee Account",
        "DISPLAY_NAME": "Audit suspended Payee Account"
      }
    ]
  },
  {
    "PROCESS_ID": 360,
    "DESCRIPTION": "Process MOU Collection",
    "name": "nfmProcessMOUCollection",
    "Activities": [
      {
        "ACTIVITY_ID": 301,
        "NAME": "Create Recovery",
        "DISPLAY_NAME": "Create Recovery"
      },
      {
        "ACTIVITY_ID": 302,
        "NAME": "Approve Recovery",
        "DISPLAY_NAME": "Approve Recovery"
      },
      {
        "ACTIVITY_ID": 303,
        "NAME": "Monitor MOU Repayment",
        "DISPLAY_NAME": "Monitor MOU Repayment"
      }
    ]
  },
  {
    "PROCESS_ID": 361,
    "DESCRIPTION": "Process Person Demographic",
    "name": "nfmProcessPersonDemographic",
    "Activities": [
      {
        "ACTIVITY_ID": 304,
        "NAME": "Modify Person",
        "DISPLAY_NAME": "Modify Person"
      },
      {
        "ACTIVITY_ID": 305,
        "NAME": "Audit Person",
        "DISPLAY_NAME": "Audit Person"
      }
    ]
  },
  {
    "PROCESS_ID": 362,
    "DESCRIPTION": "MSS Process Job Service Retirement Application",
    "name": "nfmMSSProcessJobServiceRetirementApplication",
    "Activities": [
      {
        "ACTIVITY_ID": 308,
        "NAME": "Enter Job Service Retirement Application Data",
        "DISPLAY_NAME": "Enter Job Service Retirement Application Data"
      },
      {
        "ACTIVITY_ID": 309,
        "NAME": "Approve Job Service Retirement Application Calculation",
        "DISPLAY_NAME": "Approve Job Service Retirement Application Calculation"
      },
      {
        "ACTIVITY_ID": 310,
        "NAME": "Enter Payee Account Details",
        "DISPLAY_NAME": "Enter Payee Account Details"
      },
      {
        "ACTIVITY_ID": 311,
        "NAME": "Approve Payee Account",
        "DISPLAY_NAME": "Approve Payee Account"
      }
    ]
  },
  {
    "PROCESS_ID": 363,
    "DESCRIPTION": "MSS Process DC Retirement Application",
    "name": "nfmMSSProcessDCRetirementApplication",
    "Activities": [
      {
        "ACTIVITY_ID": 312,
        "NAME": "Enter DC Retirement Application Data",
        "DISPLAY_NAME": "Enter DC Retirement Application Data"
      },
      {
        "ACTIVITY_ID": 313,
        "NAME": "Audit & Approve DC Retirement Application Data",
        "DISPLAY_NAME": "Audit & Approve DC Retirement Application Data"
      }
    ]
  },
  {
    "PROCESS_ID": 364,
    "DESCRIPTION": "MSS Process Disability Application",
    "name": "nfmMSSProcessDisabilityApplication",
    "Activities": [
      {
        "ACTIVITY_ID": 314,
        "NAME": "Enter Disability Application Data",
        "DISPLAY_NAME": "Enter Disability Application Data"
      },
      {
        "ACTIVITY_ID": 315,
        "NAME": "Approve Disability Application Calculation",
        "DISPLAY_NAME": "Approve Disability Application Calculation"
      },
      {
        "ACTIVITY_ID": 316,
        "NAME": "Enter Payee Account Details",
        "DISPLAY_NAME": "Enter Payee Account Details"
      },
      {
        "ACTIVITY_ID": 317,
        "NAME": "Approve Payee Account",
        "DISPLAY_NAME": "Approve Payee Account"
      }
    ]
  },
  {
    "PROCESS_ID": 365,
    "DESCRIPTION": "MSS Process Deferred Retirement Application",
    "name": "nfmMSSProcessDeferredRetirementApplication",
    "Activities": [
      {
        "ACTIVITY_ID": 318,
        "NAME": "Enter Deferred Retirement Application Data",
        "DISPLAY_NAME": "Enter Deferred Retirement Application Data"
      }
    ]
  },
  {
    "PROCESS_ID": 366,
    "DESCRIPTION": "MSS Process Refund Application and Calculation",
    "name": "nfmMSSProcessRefundApplicationandCalculation",
    "Activities": [
      {
        "ACTIVITY_ID": 319,
        "NAME": "Review and Enter Refund Application Data",
        "DISPLAY_NAME": "Review and Enter Refund Application Data"
      },
      {
        "ACTIVITY_ID": 320,
        "NAME": "Validate Application and Calculation",
        "DISPLAY_NAME": "Validate Application and Calculation"
      },
      {
        "ACTIVITY_ID": 321,
        "NAME": "Enter Payee Account Information",
        "DISPLAY_NAME": "Enter Payee Account Information"
      },
      {
        "ACTIVITY_ID": 322,
        "NAME": "Validate Payee Account",
        "DISPLAY_NAME": "Validate Payee Account"
      }
    ]
  },
  {
    "PROCESS_ID": 367,
    "DESCRIPTION": "Enroll Retiree Cobra Insurance Plans",
    "name": "nfmEnrollRetireeInsurancePlans",
    "Activities": [
      {
        "ACTIVITY_ID": 323,
        "NAME": "Enter Plan Enrollment Data",
        "DISPLAY_NAME": "Enter Plan Enrollment Data"
      },
      {
        "ACTIVITY_ID": 324,
        "NAME": "Audit Plan Enrollment Data",
        "DISPLAY_NAME": "Audit Plan Enrollment Data"
      }
    ]
  },
  {
    "PROCESS_ID": 368,
    "DESCRIPTION": "Enroll COBRA Insurance Plans",
    "name": "nfmEnrollCOBRAInsurancePlans",
    "Activities": [
      {
        "ACTIVITY_ID": 325,
        "NAME": "Enter Plan Enrollment Data",
        "DISPLAY_NAME": "Enter Plan Enrollment Data"
      },
      {
        "ACTIVITY_ID": 326,
        "NAME": "Audit Plan Enrollment Data",
        "DISPLAY_NAME": "Audit Plan Enrollment Data"
      }
    ]
  },
  {
    "PROCESS_ID": 369,
    "DESCRIPTION": "MSS Process DB Retirement Application",
    "name": "nfmMSSProcessDBRetirementApplication",
    "Activities": [
      {
        "ACTIVITY_ID": 331,
        "NAME": "Enter Retirement Application Data",
        "DISPLAY_NAME": "Enter Retirement Application Data"
      },
      {
        "ACTIVITY_ID": 332,
        "NAME": "Approve Retirement Application Calculation",
        "DISPLAY_NAME": "Approve Retirement Application Calculation"
      },
      {
        "ACTIVITY_ID": 333,
        "NAME": "Enter Payee Account Details",
        "DISPLAY_NAME": "Enter Payee Account Details"
      },
      {
        "ACTIVITY_ID": 334,
        "NAME": "Approve Payee Account",
        "DISPLAY_NAME": "Approve Payee Account"
      }
    ]
  },
  {
    "PROCESS_ID": 370,
    "DESCRIPTION": "Employer Payment Election",
    "name": "nfmEmployerPaymentElection",
    "Activities": [
      {
        "ACTIVITY_ID": 328,
        "NAME": "Process Employer Payment Member Type",
        "DISPLAY_NAME": "Process Employer Payment Member Type"
      }
    ]
  },
  {
    "PROCESS_ID": 371,
    "DESCRIPTION": "Process MOU Death Collection",
    "name": "nfmPayeeAccountDeathNotification",
    "Activities": [
      {
        "ACTIVITY_ID": 335,
        "NAME": "Process Death Overpayment Recovery",
        "DISPLAY_NAME": "Process Death Overpayment Recovery"
      },
      {
        "ACTIVITY_ID": 336,
        "NAME": "Monitor Death MOU Repayment",
        "DISPLAY_NAME": "Monitor Death MOU Repayment"
      }
    ]
  },
  {
    "PROCESS_ID": 374,
    "DESCRIPTION": "Process Employer Report Penalty",
    "name": "nfmProcessEmployerReportPenalty",
    "Activities": [
      {
        "ACTIVITY_ID": 341,
        "NAME": "Approve Employer Report Penalty",
        "DISPLAY_NAME": "Approve Employer Report Penalty"
      }
    ]
  },
  {
    "PROCESS_ID": 375,
    "DESCRIPTION": "Maintain Line of Duty Survivor",
    "name": "nfmMaintainLineOfDutySurvivor",
    "Activities": [
      {
        "ACTIVITY_ID": 342,
        "NAME": "Research age of Line of Duty Survivor",
        "DISPLAY_NAME": "Research age of Line of Duty Survivor"
      }
    ]
  },
  {
    "PROCESS_ID": 376,
    "DESCRIPTION": "Process Marital Status Change",
    "name": "nfmProcessMaritalStatusChange",
    "Activities": [
      {
        "ACTIVITY_ID": 343,
        "NAME": "Update Enrollment and Dependents",
        "DISPLAY_NAME": "Update Enrollment and Dependents"
      }
    ]
  },
  {
    "PROCESS_ID": 377,
    "DESCRIPTION": "Service Purchase Payment Installments Employment Change",
    "name": "nfmServicePurchasePaymentInstallmentsEmploymentChange",
    "Activities": [
      {
        "ACTIVITY_ID": 344,
        "NAME": "Service Purchase Payment Installments Employment Change",
        "DISPLAY_NAME": "Service Purchase Payment Installments Employment Change"
      }
    ]
  },
  {
    "PROCESS_ID": 378,
    "DESCRIPTION": "Process Missing RHIC Record",
    "name": "nfmProcessMissingRHICRecord",
    "Activities": [
      {
        "ACTIVITY_ID": 346,
        "NAME": "Process Missing RHIC Record",
        "DISPLAY_NAME": "Process Missing RHIC Record"
      }
    ]
  },
  {
    "PROCESS_ID": 379,
    "DESCRIPTION": "End Of Life Documents Received",
    "name": "nfmProcessMissingRHICRecord",
    "Activities": [
      {
        "ACTIVITY_ID": 348,
        "NAME": "End Of Life Documents Received",
        "DISPLAY_NAME": "End Of Life Documents Received"
      }
    ]
  },
  {
    "PROCESS_ID": 380,
    "DESCRIPTION": "Process Insurance MOU",
    "name": "nfmProcessInsuranceMOU",
    "Activities": [
      {
        "ACTIVITY_ID": 349,
        "NAME": "Review Insurance MOU",
        "DISPLAY_NAME": "Review Insurance MOU"
      },
      {
        "ACTIVITY_ID": 350,
        "NAME": "Monitor Insurance MOU Repayment",
        "DISPLAY_NAME": "Monitor Insurance MOU Repayment"
      }
    ]
  },
    {
    "PROCESS_ID": 381,
    "DESCRIPTION": "Person Contact Expiring",
    "name": "nfmPersonContactExpiring",
    "Activities": [
      {
        "ACTIVITY_ID": 352,
        "NAME": "Review Expiring Contact",
        "DISPLAY_NAME": "Review Expiring Contact"
      }
    ]
  },
  {
    "PROCESS_ID": 383,
    "DESCRIPTION": "Process DC Enrollment",
    "name": "nfmProcessDCEnrollment",
    "Activities": [
      {
        "ACTIVITY_ID": 356,
        "NAME": "Enter DC Additional Contribution",
        "DISPLAY_NAME": "Enter DC Additional Contribution"
      },
      {
        "ACTIVITY_ID": 357,
        "NAME": "Audit DC Additional Contribution",
        "DISPLAY_NAME": "Audit DC Additional Contribution"
      }
    ]
  }
]