<?xml version="1.0" encoding="utf-8"?>
<form ID="rptForm1099R_2014" sfwType="Report" sfwActive="True" sfwStatus="Review" sfwDescription="Form 1099R" sfwReportName="rptForm1099R_2014.rpt" version="4.0">
  <initialload>
    <custommethod sfwMethodName="rptForm1099R" />
  </initialload>
  <sfwTable ID="Main">
    <sfwRow>
      <sfwColumn>
        <sfwLabel sfwIsCaption="True" Text="Aint1099rID : " />
      </sfwColumn>
      <sfwColumn>
        <sfwTextBox ID="aint1099rID" sfwObjectField="aint1099rID" />
      </sfwColumn>
    </sfwRow>
  </sfwTable>
  <ExtraFields />
</form>