<form ID="corENR-5306" sfwResource="-1" sfwRemoteObject="busPersonAccountRetirement" sfwEntity="entPersonAccountRetirement" sfwTemplate="ENR-5306.docx" version="4.0" sfwType="Correspondence" sfwStatus="Review">
  <sfwAssociatedForms />
  <ExtraFields />
  <sfwFieldBookMarks>
    <sfwFieldBookMark ID="ImgImage" sfwDataType="sfwImageFile" sfwImageWidth="8.5" sfwEntityField="IstrImage" />
    <sfwFieldBookMark ID="DateofFirstNotice" sfwDataFormat="{0:d}" sfwDataType="datetime" sfwEntityField="objHb1040Communication.LetterGeneratedDate1" />
  </sfwFieldBookMarks>
  <sfwQueryBookMarks />
  <sfwTableBookMarks />
  <sfwRepeaters />
  <sfwQueryForm />
  <sfwRuleBookmarks />
  <sfwHyperlinkBookmarks />
  <sfwChildTemplateBookmarks />
</form>