<?xml version="1.0" encoding="utf-8"?>
<form ID="corAPP-7100" sfwActive="True" sfwDescription="" sfwStatus="Valid" sfwRemoteObject="busRetirementDisabilityApplication" sfwType="Correspondence" sfwTemplate="APP-7100.docx" sfwConditionalRule="" version="4.0" sfwEntity="entRetirementDisabilityApplication">
  <sfwFieldBookMarks>
    <sfwFieldBookMark ID="PlanId" />
    <sfwFieldBookMark ID="ImgImage" sfwDataType="sfwImageFile" sfwImageWidth="8.5" sfwEntityField="IstrImage" />
  </sfwFieldBookMarks>
  <sfwQueryBookMarks>
    <sfwQueryBookMark ID="Reason(s)ForDenial" sfwDataType="String" />
    <sfwQueryBookMark ID="CertifiedLetterNumber" sfwDataType="String" />
  </sfwQueryBookMarks>
  <sfwQueryForm>
    <sfwTable ID="tblCriteria">
      <sfwRow>
        <sfwColumn>
          <sfwLabel ID="capReason(s)ForDenial" Text="Reason(s) For Denial :" sfwIsCaption="True" />
        </sfwColumn>
        <sfwColumn>
          <sfwTextBox ID="txtReason(s)ForDenial" sfwQueryID="Reason(s)ForDenial" />
        </sfwColumn>
      </sfwRow>
      <sfwRow>
        <sfwColumn>
          <sfwLabel ID="capCertifiedLetterNumber" Text="Certified Letter Number :" sfwIsCaption="True" />
        </sfwColumn>
        <sfwColumn>
          <sfwTextBox ID="txtCertifiedLetterNumber" sfwQueryID="CertifiedLetterNumber" />
        </sfwColumn>
      </sfwRow>
    </sfwTable>
  </sfwQueryForm>
</form>